ncloud_loadbalancer/__init__.py
ncloud_loadbalancer/api_client.py
ncloud_loadbalancer/configuration.py
ncloud_loadbalancer/rest.py
ncloud_loadbalancer/api/__init__.py
ncloud_loadbalancer/api/v2_api.py
ncloud_loadbalancer/model/__init__.py
ncloud_loadbalancer/model/access_control_group.py
ncloud_loadbalancer/model/add_load_balancer_ssl_certificate_request.py
ncloud_loadbalancer/model/add_load_balancer_ssl_certificate_response.py
ncloud_loadbalancer/model/change_load_balanced_server_instances_request.py
ncloud_loadbalancer/model/change_load_balanced_server_instances_response.py
ncloud_loadbalancer/model/change_load_balancer_instance_configuration_request.py
ncloud_loadbalancer/model/change_load_balancer_instance_configuration_response.py
ncloud_loadbalancer/model/common_code.py
ncloud_loadbalancer/model/create_load_balancer_instance_request.py
ncloud_loadbalancer/model/create_load_balancer_instance_response.py
ncloud_loadbalancer/model/delete_load_balancer_instances_request.py
ncloud_loadbalancer/model/delete_load_balancer_instances_response.py
ncloud_loadbalancer/model/delete_load_balancer_ssl_certificate_request.py
ncloud_loadbalancer/model/delete_load_balancer_ssl_certificate_response.py
ncloud_loadbalancer/model/get_load_balanced_server_instance_list_request.py
ncloud_loadbalancer/model/get_load_balanced_server_instance_list_response.py
ncloud_loadbalancer/model/get_load_balancer_instance_list_request.py
ncloud_loadbalancer/model/get_load_balancer_instance_list_response.py
ncloud_loadbalancer/model/get_load_balancer_ssl_certificate_list_request.py
ncloud_loadbalancer/model/get_load_balancer_ssl_certificate_list_response.py
ncloud_loadbalancer/model/get_load_balancer_target_server_instance_list_request.py
ncloud_loadbalancer/model/get_load_balancer_target_server_instance_list_response.py
ncloud_loadbalancer/model/load_balanced_server_instance.py
ncloud_loadbalancer/model/load_balancer_instance.py
ncloud_loadbalancer/model/load_balancer_rule.py
ncloud_loadbalancer-1.1.1.dist-info/LICENSE
ncloud_loadbalancer-1.1.1.dist-info/METADATA
ncloud_loadbalancer-1.1.1.dist-info/WHEEL
ncloud_loadbalancer-1.1.1.dist-info/top_level.txt
ncloud_loadbalancer-1.1.1.dist-info/RECORD
