Metadata-Version: 1.0
Name: ncloud-loadbalancer
Version: 1.1.1
Summary: loadbalancer
Home-page: UNKNOWN
Author: UNKNOWN
Author-email: UNKNOWN
License: UNKNOWN
Keywords: loadbalancer
Platform: UNKNOWN
